home_clean_home/__init__.py
home_clean_home/__main__.py
home_clean_home/load.py
home_clean_home/server.py
home_clean_home/docs/hch_knowledge_base_ref.xlsx
home_clean_home-0.2.0.dist-info/METADATA
home_clean_home-0.2.0.dist-info/WHEEL
home_clean_home-0.2.0.dist-info/entry_points.txt
home_clean_home-0.2.0.dist-info/RECORD
